pysilu-0.1.6.dist-info/licenses/LICENSE
silu/__init__.py
silu/__main__.py
silu/ast_processor.py
silu/cli.py
silu/interpreter.py
silu/ir_common.py
silu/ir_generator.py
silu/ir_interpreter.py
silu/ir_to_source.py
silu/ir_utils.py
silu/silu_ir_to_llvm.py
silu/symbolic_executor.py
silu/symbolic_executor_wrapper.py
silu/symbolic_pathlib.py
silu/symbolic_utils.py
silu/symbolic/__init__.py
silu/symbolic/builtin_utils.py
silu/symbolic/condition_utils.py
silu/symbolic/exceptions.py
silu/symbolic/loop_utils.py
silu/symbolic/report_utils.py
silu/symbolic/z3_utils.py
pysilu-0.1.6.dist-info/METADATA
pysilu-0.1.6.dist-info/WHEEL
pysilu-0.1.6.dist-info/entry_points.txt
pysilu-0.1.6.dist-info/top_level.txt
pysilu-0.1.6.dist-info/RECORD
