Metadata-Version: 2.4
Name: pysilu
Version: 0.1.6
Summary: A simple AI programming language
Home-page: https://github.com/askender/silu
Author: askender
Author-email: askender <askender43@gmail.com>
License-Expression: MIT
Classifier: Programming Language :: Python :: 3
Classifier: Operating System :: OS Independent
Requires-Python: >=3.6
License-File: LICENSE
Requires-Dist: llvmlite>=0.36.0
Requires-Dist: mlir>=0.0.1
Requires-Dist: pycparser>=2.21
Requires-Dist: z3-solver>=4.12.0
Requires-Dist: loguru>=0.7.2
Dynamic: author
Dynamic: home-page
Dynamic: license-file
Dynamic: requires-python
